pipelineutils/__init__.py
pipelineutils/pipelineutils.py
pipelineutils-1.0.7.dist-info/METADATA
pipelineutils-1.0.7.dist-info/WHEEL
pipelineutils-1.0.7.dist-info/top_level.txt
pipelineutils-1.0.7.dist-info/RECORD
