Metadata-Version: 2.1
Name: pipelineutils
Version: 1.0.7
Summary: Drone pipeline workflow utilities
Home-page: https://terraref.org
Author: Chris Schnaufer
Author-email: schnaufer@email.arizona.edu
License: BSD
Project-URL: Source, https://github.com/terraref/drone-pipeline
Project-URL: Tracker, https://github.com/terraref/drone-pipeline/issues
Keywords: terraref,clowder,field crop,phenomics,computer vision,remote sensing,drone,pipeline
Platform: UNKNOWN
Classifier: Development Status :: 4 - Beta
Classifier: Intended Audience :: Science/Research
Classifier: Topic :: Scientific/Engineering :: Bio-Informatics
Classifier: Topic :: Database
Classifier: Topic :: Scientific/Engineering :: GIS
Classifier: Topic :: Utilities
Classifier: License :: OSI Approved :: BSD License
Classifier: Natural Language :: English
Classifier: Programming Language :: Python :: 3.7
Requires-Dist: requests
